citesdoc_110/__init__.py
citesdoc_110/api_client.py
citesdoc_110/configuration.py
citesdoc_110/rest.py
citesdoc_110/api/__init__.py
citesdoc_110/api/additional_api.py
citesdoc_110/api/admins_api.py
citesdoc_110/api/attachments_api.py
citesdoc_110/api/developers_api.py
citesdoc_110/api/permit_api.py
citesdoc_110/api/public_api.py
citesdoc_110/api/registration_cards_api.py
citesdoc_110/api/statement_api.py
citesdoc_110/models/__init__.py
citesdoc_110/models/additional_entry_type.py
citesdoc_110/models/agree_type.py
citesdoc_110/models/authoritative_signatory_person_type.py
citesdoc_110/models/base_entry_list_type.py
citesdoc_110/models/cites_document_additional_entry_list_type.py
citesdoc_110/models/cites_document_additional_type.py
citesdoc_110/models/cites_document_attachment_list_type.py
citesdoc_110/models/cites_document_attachment_type.py
citesdoc_110/models/cites_document_entry_list_type.py
citesdoc_110/models/cites_document_principal_type.py
citesdoc_110/models/cites_document_registration_card_type.py
citesdoc_110/models/cites_document_statement_certificate_request_type.py
citesdoc_110/models/cites_document_statement_certificate_type.py
citesdoc_110/models/cites_document_statement_permit_type.py
citesdoc_110/models/cites_document_template_type.py
citesdoc_110/models/cites_document_xfdf_list_type.py
citesdoc_110/models/cites_document_xfdf_type.py
citesdoc_110/models/cites_document_xfdf_type_identifier.py
citesdoc_110/models/cites_document_xfdf_type_template_file.py
citesdoc_110/models/citese_permit_type.py
citesdoc_110/models/code_type.py
citesdoc_110/models/conditions_type.py
citesdoc_110/models/country_id_type.py
citesdoc_110/models/cross_border_regulatory_procedure_type.py
citesdoc_110/models/customs_goods_type.py
citesdoc_110/models/customs_permit_type.py
citesdoc_110/models/cz_cites_permit_type.py
citesdoc_110/models/document_authentication_type.py
citesdoc_110/models/document_code_type.py
citesdoc_110/models/document_context_parameter_type.py
sysnet_citesdoc110-1.1.0.4.dist-info/LICENSE
sysnet_citesdoc110-1.1.0.4.dist-info/METADATA
sysnet_citesdoc110-1.1.0.4.dist-info/WHEEL
sysnet_citesdoc110-1.1.0.4.dist-info/top_level.txt
sysnet_citesdoc110-1.1.0.4.dist-info/RECORD
