Metadata-Version: 2.1
Name: sysnet-citesdoc110
Version: 1.1.0.4
Summary: CITES Documents data controller REST API 1.1.0
Home-page: 
Author-email: Radim Jaeger <rjaeger@sysnet.cz>
License: Apache License
Project-URL: Homepage, https://github.com/SYSNET-CZ/swagger/tree/main/clients/citesdoc_110
Classifier: Programming Language :: Python :: 3
Classifier: License :: OSI Approved :: Apache Software License
Classifier: Operating System :: OS Independent
Classifier: Topic :: Internet :: WWW/HTTP :: Dynamic Content
Requires-Python: >=3.9
License-File: LICENSE
